<annotation>
  <folder>input</folder>
  <filename>screenshot1705422791919.png</filename>
  <path>E:\Mine\Code\pyCode\OpenLabeling-master\main\input\screenshot1705422791919.png</path>
  <source>
    <database>Unknown</database>
  </source>
  <size>
    <width>1920</width>
    <height>1080</height>
    <depth>3</depth>
  </size>
  <segmented>0</segmented>
  <object>
    <name>tree</name>
    <pose>Unspecified</pose>
    <truncated>0</truncated>
    <difficult>0</difficult>
    <bndbox>
      <xmin>1328</xmin>
      <ymin>20</ymin>
      <xmax>1374</xmax>
      <ymax>541</ymax>
    </bndbox>
  </object>
  <object>
    <name>tree</name>
    <pose>Unspecified</pose>
    <truncated>0</truncated>
    <difficult>0</difficult>
    <bndbox>
      <xmin>716</xmin>
      <ymin>27</ymin>
      <xmax>749</xmax>
      <ymax>272</ymax>
    </bndbox>
  </object>
  <object>
    <name>tree</name>
    <pose>Unspecified</pose>
    <truncated>0</truncated>
    <difficult>0</difficult>
    <bndbox>
      <xmin>418</xmin>
      <ymin>17</ymin>
      <xmax>454</xmax>
      <ymax>267</ymax>
    </bndbox>
  </object>
  <object>
    <name>tree</name>
    <pose>Unspecified</pose>
    <truncated>0</truncated>
    <difficult>0</difficult>
    <bndbox>
      <xmin>321</xmin>
      <ymin>79</ymin>
      <xmax>350</xmax>
      <ymax>226</ymax>
    </bndbox>
  </object>
  <object>
    <name>tree</name>
    <pose>Unspecified</pose>
    <truncated>0</truncated>
    <difficult>0</difficult>
    <bndbox>
      <xmin>244</xmin>
      <ymin>72</ymin>
      <xmax>268</xmax>
      <ymax>192</ymax>
    </bndbox>
  </object>
  <object>
    <name>tree</name>
    <pose>Unspecified</pose>
    <truncated>0</truncated>
    <difficult>0</difficult>
    <bndbox>
      <xmin>1630</xmin>
      <ymin>110</ymin>
      <xmax>1655</xmax>
      <ymax>487</ymax>
    </bndbox>
  </object>
  <object>
    <name>stone</name>
    <pose>Unspecified</pose>
    <truncated>0</truncated>
    <difficult>0</difficult>
    <bndbox>
      <xmin>1206</xmin>
      <ymin>654</ymin>
      <xmax>1432</xmax>
      <ymax>848</ymax>
    </bndbox>
  </object>
</annotation>
