<annotation>
  <folder>input</folder>
  <filename>screenshot1705424764593.png</filename>
  <path>E:\Mine\Code\pyCode\OpenLabeling-master\main\input\screenshot1705424764593.png</path>
  <source>
    <database>Unknown</database>
  </source>
  <size>
    <width>1920</width>
    <height>1080</height>
    <depth>3</depth>
  </size>
  <segmented>0</segmented>
  <object>
    <name>zombie</name>
    <pose>Unspecified</pose>
    <truncated>0</truncated>
    <difficult>0</difficult>
    <bndbox>
      <xmin>1089</xmin>
      <ymin>309</ymin>
      <xmax>1116</xmax>
      <ymax>365</ymax>
    </bndbox>
  </object>
  <object>
    <name>zombie</name>
    <pose>Unspecified</pose>
    <truncated>0</truncated>
    <difficult>0</difficult>
    <bndbox>
      <xmin>1000</xmin>
      <ymin>313</ymin>
      <xmax>1028</xmax>
      <ymax>357</ymax>
    </bndbox>
  </object>
  <object>
    <name>zombie</name>
    <pose>Unspecified</pose>
    <truncated>0</truncated>
    <difficult>0</difficult>
    <bndbox>
      <xmin>922</xmin>
      <ymin>296</ymin>
      <xmax>950</xmax>
      <ymax>350</ymax>
    </bndbox>
  </object>
  <object>
    <name>zombie</name>
    <pose>Unspecified</pose>
    <truncated>0</truncated>
    <difficult>0</difficult>
    <bndbox>
      <xmin>862</xmin>
      <ymin>302</ymin>
      <xmax>882</xmax>
      <ymax>344</ymax>
    </bndbox>
  </object>
  <object>
    <name>zombie</name>
    <pose>Unspecified</pose>
    <truncated>0</truncated>
    <difficult>0</difficult>
    <bndbox>
      <xmin>740</xmin>
      <ymin>293</ymin>
      <xmax>768</xmax>
      <ymax>339</ymax>
    </bndbox>
  </object>
  <object>
    <name>tree</name>
    <pose>Unspecified</pose>
    <truncated>0</truncated>
    <difficult>0</difficult>
    <bndbox>
      <xmin>609</xmin>
      <ymin>35</ymin>
      <xmax>701</xmax>
      <ymax>443</ymax>
    </bndbox>
  </object>
  <object>
    <name>tree</name>
    <pose>Unspecified</pose>
    <truncated>0</truncated>
    <difficult>0</difficult>
    <bndbox>
      <xmin>1430</xmin>
      <ymin>27</ymin>
      <xmax>1449</xmax>
      <ymax>432</ymax>
    </bndbox>
  </object>
</annotation>
