<annotation>
  <folder>input</folder>
  <filename>screenshot1705422894577.png</filename>
  <path>E:\Mine\Code\pyCode\OpenLabeling-master\main\input\screenshot1705422894577.png</path>
  <source>
    <database>Unknown</database>
  </source>
  <size>
    <width>1920</width>
    <height>1080</height>
    <depth>3</depth>
  </size>
  <segmented>0</segmented>
  <object>
    <name>tree</name>
    <pose>Unspecified</pose>
    <truncated>0</truncated>
    <difficult>0</difficult>
    <bndbox>
      <xmin>894</xmin>
      <ymin>18</ymin>
      <xmax>942</xmax>
      <ymax>480</ymax>
    </bndbox>
  </object>
  <object>
    <name>tree</name>
    <pose>Unspecified</pose>
    <truncated>0</truncated>
    <difficult>0</difficult>
    <bndbox>
      <xmin>848</xmin>
      <ymin>34</ymin>
      <xmax>868</xmax>
      <ymax>454</ymax>
    </bndbox>
  </object>
  <object>
    <name>tree</name>
    <pose>Unspecified</pose>
    <truncated>0</truncated>
    <difficult>0</difficult>
    <bndbox>
      <xmin>520</xmin>
      <ymin>153</ymin>
      <xmax>541</xmax>
      <ymax>336</ymax>
    </bndbox>
  </object>
  <object>
    <name>tree</name>
    <pose>Unspecified</pose>
    <truncated>0</truncated>
    <difficult>0</difficult>
    <bndbox>
      <xmin>6</xmin>
      <ymin>75</ymin>
      <xmax>119</xmax>
      <ymax>544</ymax>
    </bndbox>
  </object>
  <object>
    <name>mushroom</name>
    <pose>Unspecified</pose>
    <truncated>0</truncated>
    <difficult>0</difficult>
    <bndbox>
      <xmin>1701</xmin>
      <ymin>416</ymin>
      <xmax>1795</xmax>
      <ymax>474</ymax>
    </bndbox>
  </object>
</annotation>
