<annotation>
  <folder>input</folder>
  <filename>screenshot1705423875143.png</filename>
  <path>E:\Mine\Code\pyCode\OpenLabeling-master\main\input\screenshot1705423875143.png</path>
  <source>
    <database>Unknown</database>
  </source>
  <size>
    <width>1920</width>
    <height>1080</height>
    <depth>3</depth>
  </size>
  <segmented>0</segmented>
  <object>
    <name>berry</name>
    <pose>Unspecified</pose>
    <truncated>0</truncated>
    <difficult>0</difficult>
    <bndbox>
      <xmin>810</xmin>
      <ymin>350</ymin>
      <xmax>1002</xmax>
      <ymax>524</ymax>
    </bndbox>
  </object>
  <object>
    <name>tree</name>
    <pose>Unspecified</pose>
    <truncated>0</truncated>
    <difficult>0</difficult>
    <bndbox>
      <xmin>899</xmin>
      <ymin>0</ymin>
      <xmax>1006</xmax>
      <ymax>426</ymax>
    </bndbox>
  </object>
  <object>
    <name>tree</name>
    <pose>Unspecified</pose>
    <truncated>0</truncated>
    <difficult>0</difficult>
    <bndbox>
      <xmin>566</xmin>
      <ymin>12</ymin>
      <xmax>619</xmax>
      <ymax>312</ymax>
    </bndbox>
  </object>
  <object>
    <name>tree</name>
    <pose>Unspecified</pose>
    <truncated>0</truncated>
    <difficult>0</difficult>
    <bndbox>
      <xmin>268</xmin>
      <ymin>69</ymin>
      <xmax>329</xmax>
      <ymax>235</ymax>
    </bndbox>
  </object>
  <object>
    <name>stone</name>
    <pose>Unspecified</pose>
    <truncated>0</truncated>
    <difficult>0</difficult>
    <bndbox>
      <xmin>599</xmin>
      <ymin>353</ymin>
      <xmax>721</xmax>
      <ymax>437</ymax>
    </bndbox>
  </object>
  <object>
    <name>herb</name>
    <pose>Unspecified</pose>
    <truncated>0</truncated>
    <difficult>0</difficult>
    <bndbox>
      <xmin>331</xmin>
      <ymin>196</ymin>
      <xmax>391</xmax>
      <ymax>247</ymax>
    </bndbox>
  </object>
  <object>
    <name>herb</name>
    <pose>Unspecified</pose>
    <truncated>0</truncated>
    <difficult>0</difficult>
    <bndbox>
      <xmin>855</xmin>
      <ymin>199</ymin>
      <xmax>892</xmax>
      <ymax>261</ymax>
    </bndbox>
  </object>
  <object>
    <name>herb</name>
    <pose>Unspecified</pose>
    <truncated>0</truncated>
    <difficult>0</difficult>
    <bndbox>
      <xmin>1436</xmin>
      <ymin>272</ymin>
      <xmax>1575</xmax>
      <ymax>435</ymax>
    </bndbox>
  </object>
  <object>
    <name>zombie</name>
    <pose>Unspecified</pose>
    <truncated>0</truncated>
    <difficult>0</difficult>
    <bndbox>
      <xmin>124</xmin>
      <ymin>156</ymin>
      <xmax>168</xmax>
      <ymax>249</ymax>
    </bndbox>
  </object>
</annotation>
